fr_env_resolver/__init__.py
fr_env_resolver/__main__.py
fr_env_resolver/constants.py
fr_env_resolver/exceptions.py
fr_env_resolver/interfaces.py
fr_env_resolver/structs.py
fr_env_resolver/_internal/__init__.py
fr_env_resolver/_internal/cli/__init__.py
fr_env_resolver/_internal/cli/execute.py
fr_env_resolver/_internal/cli/main.py
fr_env_resolver/_internal/cli/parse.py
fr_env_resolver/_internal/cli/resolve.py
fr_env_resolver/_internal/core/__init__.py
fr_env_resolver/_internal/core/filters.py
fr_env_resolver/_internal/core/resolve.py
fr_env_resolver/_internal/core/validate.py
fr_env_resolver/_internal/impl/__init__.py
fr_env_resolver/_internal/impl/base_updater.py
fr_env_resolver/_internal/impl/env_updater.py
fr_env_resolver/_internal/impl/manifest_updater.py
fr_env_resolver/_internal/impl/resolver.py
fr_env_resolver/_internal/impl/tool_updater.py
fr_env_resolver-0.2.1.dist-info/licenses/LICENSE
fr_env_resolver-0.2.1.dist-info/licenses/LICENSES.txt
schema/env_context.fr_schema
schema/env_manifest.fr_schema
schema/env_tool.fr_schema
fr_env_resolver-0.2.1.dist-info/METADATA
fr_env_resolver-0.2.1.dist-info/WHEEL
fr_env_resolver-0.2.1.dist-info/entry_points.txt
fr_env_resolver-0.2.1.dist-info/top_level.txt
fr_env_resolver-0.2.1.dist-info/RECORD
