Metadata-Version: 2.4
Name: fr_env_resolver
Version: 0.2.1
Summary: Resolves an environment based on the specified context
Author-email: "alex.telford" <alex.telford@floating-rock.com>
License: MIT
Project-URL: Homepage, https://github.com/FloatingRockStudio/fr_env_resolver
Project-URL: Repository, https://github.com/FloatingRockStudio/fr_env_resolver.git
Classifier: Development Status :: 3 - Alpha
Classifier: Intended Audience :: Developers
Classifier: License :: OSI Approved :: MIT License
Classifier: Operating System :: OS Independent
Classifier: Programming Language :: Python :: 3
Classifier: Programming Language :: Python :: 3.7
Classifier: Programming Language :: Python :: 3.8
Classifier: Programming Language :: Python :: 3.9
Classifier: Programming Language :: Python :: 3.10
Classifier: Programming Language :: Python :: 3.11
Requires-Python: <4,>=3.7
License-File: LICENSE
License-File: LICENSES.txt
Requires-Dist: fr_config<1,>=0.2.0
Requires-Dist: rez<4,>=3
Requires-Dist: dacite<2,>=1.8
Requires-Dist: pyjson5<2,>=1.6
Provides-Extra: dev
Requires-Dist: pytest; extra == "dev"
Requires-Dist: pytest-cov; extra == "dev"
Dynamic: license-file
